<annotation>
  <folder>synthetic</folder>
  <filename>015_00075818-32.jpg</filename>
  <source>
    <database>labelme</database>
    <annotation>labelme</annotation>
    <image>labelme</image>
  </source>
  <size>
    <width>2550</width>
    <height>3300</height>
    <depth>3</depth>
  </size>
  <segmented>0</segmented>
  <object>
    <name>table</name>
    <bndbox>
      <xmin>474</xmin>
      <ymin>265</ymin>
      <xmax>2152</xmax>
      <ymax>2396</ymax>
    </bndbox>
  </object>
  <object>
    <name>list</name>
    <bndbox>
      <xmin>270</xmin>
      <ymin>2456</ymin>
      <xmax>1268</xmax>
      <ymax>3060</ymax>
    </bndbox>
  </object>
  <object>
    <name>text</name>
    <bndbox>
      <xmin>1393</xmin>
      <ymin>2456</ymin>
      <xmax>2351</xmax>
      <ymax>2756</ymax>
    </bndbox>
  </object>
  <object>
    <name>section</name>
    <bndbox>
      <xmin>1288</xmin>
      <ymin>2836</ymin>
      <xmax>1812</xmax>
      <ymax>2911</ymax>
    </bndbox>
  </object>
  <object>
    <name>list</name>
    <bndbox>
      <xmin>1348</xmin>
      <ymin>2931</ymin>
      <xmax>2346</xmax>
      <ymax>3045</ymax>
    </bndbox>
  </object>
</annotation>
